globalcache/__init__.py
globalcache/cache.py
globalcache-0.2.3.dist-info/LICENSE.txt
globalcache-0.2.3.dist-info/METADATA
globalcache-0.2.3.dist-info/WHEEL
globalcache-0.2.3.dist-info/top_level.txt
globalcache-0.2.3.dist-info/RECORD
