Metadata-Version: 2.1
Name: globalcache
Version: 0.2.3
Summary: Global caching for iPython and Spyder
Author-email: John Huang <johnzilla76@gmail.com>
Project-URL: Homepage, https://github.com/johnh865/globalcache
Project-URL: Issues, https://github.com/johnh865/globalcache/issues
Classifier: Programming Language :: Python :: 3
Classifier: License :: OSI Approved :: MIT License
Classifier: Operating System :: OS Independent
Requires-Python: >=3.8
License-File: LICENSE.txt
